llama_index/readers/opendal/__init__.py
llama_index/readers/opendal/base.py
llama_index/readers/opendal/azblob/__init__.py
llama_index/readers/opendal/azblob/base.py
llama_index/readers/opendal/gcs/__init__.py
llama_index/readers/opendal/gcs/base.py
llama_index/readers/opendal/s3/__init__.py
llama_index/readers/opendal/s3/base.py
llama_index_readers_opendal_reader-0.4.1.dist-info/METADATA
llama_index_readers_opendal_reader-0.4.1.dist-info/WHEEL
llama_index_readers_opendal_reader-0.4.1.dist-info/licenses/LICENSE
llama_index_readers_opendal_reader-0.4.1.dist-info/RECORD
