Metadata-Version: 2.4
Name: llama-index-readers-opendal-reader
Version: 0.4.1
Summary: llama-index readers opendal_reader integration
Author-email: Your Name <you@example.com>
Maintainer: OpenDAL Contributors
License-Expression: MIT
License-File: LICENSE
Keywords: azblob,gcs,s3,storage
Requires-Python: <4.0,>=3.9
Requires-Dist: llama-index-core<0.15,>=0.13.0
Requires-Dist: opendal
